LICENSE.txt
MANIFEST.in
README.md
setup.py
LatinUtilities/LatinUtilities.py
LatinUtilities/__init__.py
LatinUtilities/__main__.py
LatinUtilities.egg-info/PKG-INFO
LatinUtilities.egg-info/SOURCES.txt
LatinUtilities.egg-info/dependency_links.txt
LatinUtilities.egg-info/entry_points.txt
LatinUtilities.egg-info/top_level.txt