Metadata-Version: 2.1
Name: LatinUtilities
Version: 0.0.1
Summary: This package show int, hexa, binary and latin1 from int, hexa, binary or latin1.
Home-page: https://github.com/mauricelambert/LatinUtilities
Author: Maurice Lambert
Author-email: mauricelambert434@gmail.com
License: UNKNOWN
Platform: UNKNOWN
Classifier: Programming Language :: Python
Classifier: Development Status :: 5 - Production/Stable
Classifier: Environment :: Console
Classifier: Natural Language :: English
Classifier: Programming Language :: Python :: 3.9
Classifier: Operating System :: POSIX :: Linux
Classifier: Operating System :: Microsoft :: Windows
Classifier: Operating System :: MacOS
Requires-Python: >=3.6
